gsi/__init__.py
gsi/constants.py
gsi/database.py
gsi/logger.py
gsi/pg_upsert.py
gsi/utils.py
gsi_dm-0.0.3.dist-info/LICENSE
gsi_dm-0.0.3.dist-info/METADATA
gsi_dm-0.0.3.dist-info/WHEEL
gsi_dm-0.0.3.dist-info/top_level.txt
gsi_dm-0.0.3.dist-info/RECORD
